mc_pdf2txt/__init__.py
mc_pdf2txt/_version.py
mc_pdf2txt/main.py
mc_pdf2txt-0.3.0.dist-info/LICENSE
mc_pdf2txt-0.3.0.dist-info/METADATA
mc_pdf2txt-0.3.0.dist-info/WHEEL
mc_pdf2txt-0.3.0.dist-info/entry_points.txt
mc_pdf2txt-0.3.0.dist-info/top_level.txt
mc_pdf2txt-0.3.0.dist-info/RECORD
