Metadata-Version: 2.1
Name: mc-pdf2txt
Version: 0.3.0
Summary: Multi-column PDF to Text
Author-email: Toshihiro Kamiya <kamiya@mbj.nifty.com>
License: BSD 2-Clause License
Project-URL: Homepage, https://github.com/tos-kamiya/mc-pdf2txt
Classifier: Programming Language :: Python :: 3.8
Classifier: Programming Language :: Python :: 3.9
Classifier: Programming Language :: Python :: 3.10
Classifier: License :: OSI Approved :: BSD License
Classifier: Operating System :: MacOS :: MacOS X
Classifier: Operating System :: POSIX :: Linux
Classifier: Operating System :: Microsoft :: Windows
Requires-Python: >=3.8
License-File: LICENSE
